spade_bdi/__init__.py
spade_bdi/bdi.py
spade_bdi-0.3.2.dist-info/AUTHORS.rst
spade_bdi-0.3.2.dist-info/LICENSE
spade_bdi-0.3.2.dist-info/METADATA
spade_bdi-0.3.2.dist-info/WHEEL
spade_bdi-0.3.2.dist-info/top_level.txt
spade_bdi-0.3.2.dist-info/RECORD
