Metadata-Version: 2.1
Name: spade-bdi
Version: 0.3.2
Summary: Plugin for SPADE 3 MAS platform to implement BDI Agents.
Home-page: https://github.com/javipalanca/spade_bdi
Author: Sergio Frayle Pérez
Author-email: sfp932705@gmail.com
License: MIT License v3
Keywords: spade_bdi
Platform: UNKNOWN
Classifier: Development Status :: 4 - Beta
Classifier: Intended Audience :: Developers
Classifier: License :: OSI Approved :: MIT License
Classifier: Natural Language :: English
Classifier: Programming Language :: Python :: 3
Classifier: Programming Language :: Python :: 3.8
Classifier: Programming Language :: Python :: 3.9
Classifier: Programming Language :: Python :: 3.10
Classifier: Programming Language :: Python :: 3.11
Classifier: Programming Language :: Python :: 3.12
Classifier: Operating System :: MacOS :: MacOS X
Classifier: Operating System :: POSIX :: Linux
Classifier: Operating System :: Microsoft :: Windows
Classifier: Topic :: Scientific/Engineering :: Artificial Intelligence
Classifier: Topic :: Internet :: XMPP
Requires-Dist: spade (>=4.0.1)
Requires-Dist: agentspeak (>=0.2.1)
Requires-Dist: loguru (>=0.7.2)
